video2frames/__init__.py
video2frames/frame_split.py
video2frames-0.0.6.dist-info/METADATA
video2frames-0.0.6.dist-info/WHEEL
video2frames-0.0.6.dist-info/top_level.txt
video2frames-0.0.6.dist-info/RECORD
