Metadata-Version: 2.1
Name: video2frames
Version: 0.0.6
Summary: video2frames package test
Author: Joshua Taylor
Author-email: joshua.taylor@integer-tech.com
Keywords: python,first package
Classifier: Development Status :: 3 - Alpha
Classifier: Intended Audience :: Education
Classifier: Programming Language :: Python :: 2
Classifier: Programming Language :: Python :: 3
Classifier: Operating System :: MacOS :: MacOS X
Classifier: Operating System :: Microsoft :: Windows
Requires-Dist: opencv-python
